ecp_reference/__init__.py
ecp_reference/cli.py
ecp_reference/errors.py
ecp_reference/evals.py
ecp_reference/indexer.py
ecp_reference/llm_ollama.py
ecp_reference/llm_openrouter.py
ecp_reference/maintenance.py
ecp_reference/mcp_server.py
ecp_reference/packaging.py
ecp_reference/profile_constraints.py
ecp_reference/retention.py
ecp_reference/retriever.py
ecp_reference/runtime.py
ecp_reference/skill_loader.py
ecp_reference/sqlite_fts.py
ecp_reference/summary_generator.py
ecp_reference/synthesizer.py
ecp_reference/utils.py
ecp_reference/vectors.py
ecp_reference/schemas/ecp-chunk-provenance.schema.json
ecp_reference/schemas/ecp-eval-suite.schema.json
ecp_reference/schemas/ecp-index-descriptor.schema.json
ecp_reference/schemas/ecp-keyword-index.schema.json
ecp_reference/schemas/ecp-manifest.schema.json
ecp_reference/schemas/ecp-package.schema.json
ecp_reference/schemas/ecp-policy.schema.json
ecp_reference/schemas/ecp-sqlite-fts-index.schema.json
ecp_reference/schemas/ecp-vector-index.schema.json
ecp_reference-1.0.0.dist-info/licenses/LICENSE
ecp_reference-1.0.0.dist-info/METADATA
ecp_reference-1.0.0.dist-info/WHEEL
ecp_reference-1.0.0.dist-info/entry_points.txt
ecp_reference-1.0.0.dist-info/top_level.txt
ecp_reference-1.0.0.dist-info/RECORD
