Metadata-Version: 2.4
Name: ecp-reference
Version: 1.0.0
Summary: Reference implementation of Expert Context Pack (ECP) v1.0
Author-email: Mounir IDRASSI <mounir@amcrypto.org>
License: Apache-2.0
Keywords: agents,skills,memory,ecp,retrieval
Classifier: Programming Language :: Python :: 3
Classifier: License :: OSI Approved :: Apache Software License
Classifier: Operating System :: OS Independent
Requires-Python: >=3.10
License-File: LICENSE
Requires-Dist: PyYAML>=6.0
Requires-Dist: jsonschema>=4.18.0
Dynamic: license-file
